imas_simdb-0.14.1.dist-info/licenses/LICENSE.txt
simdb/__init__.py
simdb/_version.py
simdb/checksum.py
simdb/docstrings.py
simdb/json.py
simdb/notifications.py
simdb/py.typed
simdb/query.py
simdb/uri.py
simdb/cli/__init__.py
simdb/cli/__main__.py
simdb/cli/file_system.py
simdb/cli/manifest.py
simdb/cli/remote_api.py
simdb/cli/simdb.py
simdb/cli/template.yaml
simdb/cli/commands/__init__.py
simdb/cli/commands/alias.py
simdb/cli/commands/config.py
simdb/cli/commands/database.py
simdb/cli/commands/manifest.py
simdb/cli/commands/provenance.py
simdb/cli/commands/remote.py
simdb/cli/commands/simulation.py
simdb/cli/commands/utils.py
simdb/cli/commands/validators.py
simdb/config/__init__.py
simdb/config/config.py
simdb/database/__init__.py
simdb/database/database.py
simdb/database/models/__init__.py
simdb/database/models/base.py
simdb/database/models/file.py
simdb/database/models/metadata.py
simdb/database/models/simulation.py
simdb/database/models/types.py
simdb/database/models/utils.py
simdb/database/models/watcher.py
simdb/email/__init__.py
simdb/email/server.py
simdb/imas/__init__.py
simdb/imas/checksum.py
simdb/imas/imas_metadata.yaml
simdb/imas/metadata.py
simdb/imas/utils.py
simdb/remote/__init__.py
simdb/remote/app.py
simdb/remote/wsgi.py
simdb/remote/apis/__init__.py
simdb/remote/apis/files.py
simdb/remote/apis/metadata.py
simdb/remote/apis/watchers.py
simdb/remote/apis/v1/__init__.py
simdb/remote/apis/v1/simulations.py
simdb/remote/apis/v1_1/__init__.py
simdb/remote/apis/v1_1/simulations.py
simdb/remote/apis/v1_2/__init__.py
simdb/remote/apis/v1_2/sim.sql
simdb/remote/apis/v1_2/simulations.py
simdb/remote/core/__init__.py
simdb/remote/core/alias.py
simdb/remote/core/cache.py
simdb/remote/core/errors.py
simdb/remote/core/path.py
simdb/remote/core/typing.py
simdb/remote/core/auth/__init__.py
simdb/remote/core/auth/_authenticator.py
simdb/remote/core/auth/_exceptions.py
simdb/remote/core/auth/_user.py
simdb/remote/core/auth/active_directory.py
simdb/remote/core/auth/firewall.py
simdb/remote/core/auth/keycloak.py
imas_simdb-0.14.1.dist-info/METADATA
imas_simdb-0.14.1.dist-info/WHEEL
imas_simdb-0.14.1.dist-info/entry_points.txt
imas_simdb-0.14.1.dist-info/top_level.txt
imas_simdb-0.14.1.dist-info/RECORD
